{
   "tooltip" : {
      "headerFormat" : "<span style='font-size:11px'>{series.name}</span><br/>",
      "pointFormat" : "<span style='color:{point.color}'>{point.name}</span>: <b>{point.y:f}</b><br/>",
      "followPointer" : 1
   },
   "chart" : {
      "type" : "column"
   },
   "subtitle" : {
      "text" : "[Champions: 23] Last updated at 2022-10-14 07:10:32 GMT"
   },
   "plotOptions" : {
      "series" : {
         "dataLabels" : {
            "enabled" : 1,
            "format" : "{point.y}"
         },
         "borderWidth" : 0
      }
   },
   "drilldown" : {
      "series" : [
         {
            "name" : "Dario Mazzeo",
            "data" : [
               [
                  "Perl",
                  1
               ]
            ],
            "id" : "Dario Mazzeo"
         },
         {
            "name" : "Dave Cross",
            "data" : [
               [
                  "Perl",
                  2
               ]
            ],
            "id" : "Dave Cross"
         },
         {
            "name" : "Dave Jacoby",
            "data" : [
               [
                  "Perl",
                  2
               ]
            ],
            "id" : "Dave Jacoby"
         },
         {
            "data" : [
               [
                  "Perl",
                  2
               ]
            ],
            "name" : "E. Choroba",
            "id" : "E. Choroba"
         },
         {
            "name" : "Feng Chang",
            "data" : [
               [
                  "Raku",
                  2
               ]
            ],
            "id" : "Feng Chang"
         },
         {
            "name" : "Flavio Poletti",
            "data" : [
               [
                  "Perl",
                  2
               ],
               [
                  "Raku",
                  2
               ],
               [
                  "Blog",
                  2
               ]
            ],
            "id" : "Flavio Poletti"
         },
         {
            "id" : "izem",
            "name" : "izem",
            "data" : [
               [
                  "Perl",
                  2
               ]
            ]
         },
         {
            "name" : "Jaldhar H. Vyas",
            "data" : [
               [
                  "Perl",
                  2
               ],
               [
                  "Raku",
                  2
               ],
               [
                  "Blog",
                  1
               ]
            ],
            "id" : "Jaldhar H. Vyas"
         },
         {
            "id" : "James Smith",
            "data" : [
               [
                  "Perl",
                  2
               ],
               [
                  "Blog",
                  1
               ]
            ],
            "name" : "James Smith"
         },
         {
            "name" : "Julien Fiegehenn",
            "data" : [
               [
                  "Perl",
                  2
               ]
            ],
            "id" : "Julien Fiegehenn"
         },
         {
            "id" : "Kjetil Skotheim",
            "data" : [
               [
                  "Perl",
                  2
               ]
            ],
            "name" : "Kjetil Skotheim"
         },
         {
            "name" : "Laurent Rosenfeld",
            "data" : [
               [
                  "Perl",
                  2
               ],
               [
                  "Raku",
                  2
               ],
               [
                  "Blog",
                  1
               ]
            ],
            "id" : "Laurent Rosenfeld"
         },
         {
            "id" : "Luca Ferrari",
            "data" : [
               [
                  "Raku",
                  2
               ],
               [
                  "Blog",
                  6
               ]
            ],
            "name" : "Luca Ferrari"
         },
         {
            "id" : "Mark Anderson",
            "name" : "Mark Anderson",
            "data" : [
               [
                  "Raku",
                  2
               ]
            ]
         },
         {
            "id" : "Matthew Neleigh",
            "data" : [
               [
                  "Perl",
                  2
               ]
            ],
            "name" : "Matthew Neleigh"
         },
         {
            "id" : "Peter Campbell Smith",
            "data" : [
               [
                  "Perl",
                  2
               ],
               [
                  "Blog",
                  1
               ]
            ],
            "name" : "Peter Campbell Smith"
         },
         {
            "data" : [
               [
                  "Perl",
                  2
               ],
               [
                  "Raku",
                  2
               ]
            ],
            "name" : "Robert DiCicco",
            "id" : "Robert DiCicco"
         },
         {
            "id" : "Robert Ransbottom",
            "name" : "Robert Ransbottom",
            "data" : [
               [
                  "Raku",
                  2
               ]
            ]
         },
         {
            "id" : "Roger Bell_West",
            "name" : "Roger Bell_West",
            "data" : [
               [
                  "Perl",
                  2
               ],
               [
                  "Raku",
                  1
               ]
            ]
         },
         {
            "data" : [
               [
                  "Perl",
                  2
               ],
               [
                  "Raku",
                  2
               ],
               [
                  "Blog",
                  1
               ]
            ],
            "name" : "Stephen G. Lynn",
            "id" : "Stephen G. Lynn"
         },
         {
            "id" : "Tim Potapov",
            "name" : "Tim Potapov",
            "data" : [
               [
                  "Perl",
                  2
               ]
            ]
         },
         {
            "id" : "Ulrich Rieke",
            "data" : [
               [
                  "Perl",
                  1
               ],
               [
                  "Raku",
                  2
               ]
            ],
            "name" : "Ulrich Rieke"
         },
         {
            "id" : "W. Luis Mochan",
            "data" : [
               [
                  "Perl",
                  2
               ],
               [
                  "Blog",
                  1
               ]
            ],
            "name" : "W. Luis Mochan"
         }
      ]
   },
   "legend" : {
      "enabled" : 0
   },
   "xAxis" : {
      "type" : "category"
   },
   "series" : [
      {
         "data" : [
            {
               "name" : "Dario Mazzeo",
               "y" : 1,
               "drilldown" : "Dario Mazzeo"
            },
            {
               "y" : 2,
               "drilldown" : "Dave Cross",
               "name" : "Dave Cross"
            },
            {
               "name" : "Dave Jacoby",
               "drilldown" : "Dave Jacoby",
               "y" : 2
            },
            {
               "drilldown" : "E. Choroba",
               "y" : 2,
               "name" : "E. Choroba"
            },
            {
               "y" : 2,
               "drilldown" : "Feng Chang",
               "name" : "Feng Chang"
            },
            {
               "name" : "Flavio Poletti",
               "y" : 6,
               "drilldown" : "Flavio Poletti"
            },
            {
               "name" : "izem",
               "y" : 2,
               "drilldown" : "izem"
            },
            {
               "name" : "Jaldhar H. Vyas",
               "y" : 5,
               "drilldown" : "Jaldhar H. Vyas"
            },
            {
               "name" : "James Smith",
               "drilldown" : "James Smith",
               "y" : 3
            },
            {
               "y" : 2,
               "drilldown" : "Julien Fiegehenn",
               "name" : "Julien Fiegehenn"
            },
            {
               "y" : 2,
               "drilldown" : "Kjetil Skotheim",
               "name" : "Kjetil Skotheim"
            },
            {
               "y" : 5,
               "drilldown" : "Laurent Rosenfeld",
               "name" : "Laurent Rosenfeld"
            },
            {
               "name" : "Luca Ferrari",
               "drilldown" : "Luca Ferrari",
               "y" : 8
            },
            {
               "y" : 2,
               "drilldown" : "Mark Anderson",
               "name" : "Mark Anderson"
            },
            {
               "drilldown" : "Matthew Neleigh",
               "y" : 2,
               "name" : "Matthew Neleigh"
            },
            {
               "name" : "Peter Campbell Smith",
               "drilldown" : "Peter Campbell Smith",
               "y" : 3
            },
            {
               "name" : "Robert DiCicco",
               "y" : 4,
               "drilldown" : "Robert DiCicco"
            },
            {
               "drilldown" : "Robert Ransbottom",
               "y" : 2,
               "name" : "Robert Ransbottom"
            },
            {
               "drilldown" : "Roger Bell_West",
               "y" : 3,
               "name" : "Roger Bell_West"
            },
            {
               "drilldown" : "Stephen G. Lynn",
               "y" : 5,
               "name" : "Stephen G. Lynn"
            },
            {
               "name" : "Tim Potapov",
               "y" : 2,
               "drilldown" : "Tim Potapov"
            },
            {
               "name" : "Ulrich Rieke",
               "y" : 3,
               "drilldown" : "Ulrich Rieke"
            },
            {
               "name" : "W. Luis Mochan",
               "drilldown" : "W. Luis Mochan",
               "y" : 3
            }
         ],
         "name" : "The Weekly Challenge - 186",
         "colorByPoint" : 1
      }
   ],
   "yAxis" : {
      "title" : {
         "text" : "Total Solutions"
      }
   },
   "title" : {
      "text" : "The Weekly Challenge - 186"
   }
}
