{
   "subtitle" : {
      "text" : "Click the columns to drilldown the score breakdown. Last updated at 2020-10-06 06:16:46 GMT"
   },
   "title" : {
      "text" : "Perl Weekly Challenge Leaders (TOP 50)"
   },
   "plotOptions" : {
      "series" : {
         "dataLabels" : {
            "format" : "{point.y}",
            "enabled" : 1
         },
         "borderWidth" : 0
      }
   },
   "legend" : {
      "enabled" : "false"
   },
   "xAxis" : {
      "type" : "category"
   },
   "tooltip" : {
      "followPointer" : "true",
      "pointFormat" : "<span style=\"color:{point.color}\">{point.name}</span>: <b>{point.y:f}</b><br/>",
      "headerFormat" : "<span style=\"font-size:11px\"></span>"
   },
   "series" : [
      {
         "colorByPoint" : "true",
         "data" : [
            {
               "name" : "#1: Laurent Rosenfeld",
               "y" : 890,
               "drilldown" : "Laurent Rosenfeld"
            },
            {
               "drilldown" : "Jaldhar H. Vyas",
               "name" : "#2: Jaldhar H. Vyas",
               "y" : 672
            },
            {
               "y" : 578,
               "name" : "#3: Roger Bell_West",
               "drilldown" : "Roger Bell_West"
            },
            {
               "drilldown" : "Arne Sommer",
               "name" : "#4: Arne Sommer",
               "y" : 542
            },
            {
               "name" : "#5: Javier Luque",
               "y" : 460,
               "drilldown" : "Javier Luque"
            },
            {
               "name" : "#6: Ruben Westerberg",
               "y" : 452,
               "drilldown" : "Ruben Westerberg"
            },
            {
               "drilldown" : "Colin Crain",
               "y" : 430,
               "name" : "#7: Colin Crain"
            },
            {
               "drilldown" : "E. Choroba",
               "y" : 412,
               "name" : "#8: E. Choroba"
            },
            {
               "drilldown" : "Athanasius",
               "y" : 408,
               "name" : "#9: Athanasius"
            },
            {
               "drilldown" : "Mohammad S Anwar",
               "y" : 384,
               "name" : "#10: Mohammad S Anwar"
            },
            {
               "drilldown" : "Adam Russell",
               "name" : "#11: Adam Russell",
               "y" : 374
            },
            {
               "drilldown" : "Joelle Maslak",
               "name" : "#12: Joelle Maslak",
               "y" : 334
            },
            {
               "name" : "#13: Simon Proctor",
               "y" : 316,
               "drilldown" : "Simon Proctor"
            },
            {
               "drilldown" : "Dave Jacoby",
               "y" : 310,
               "name" : "#14: Dave Jacoby"
            },
            {
               "y" : 278,
               "name" : "#15: Ryan Thompson",
               "drilldown" : "Ryan Thompson"
            },
            {
               "drilldown" : "Duncan C. White",
               "name" : "#16: Duncan C. White",
               "y" : 270
            },
            {
               "name" : "#17: Luca Ferrari",
               "y" : 268,
               "drilldown" : "Luca Ferrari"
            },
            {
               "drilldown" : "Ulrich Rieke",
               "name" : "#18: Ulrich Rieke",
               "y" : 258
            },
            {
               "y" : 230,
               "name" : "#19: Andrezgz",
               "drilldown" : "Andrezgz"
            },
            {
               "y" : 216,
               "name" : "#20: Yet Ebreo",
               "drilldown" : "Yet Ebreo"
            },
            {
               "name" : "#21: Noud Aldenhoven",
               "y" : 188,
               "drilldown" : "Noud Aldenhoven"
            },
            {
               "drilldown" : "Kevin Colyer",
               "name" : "#22: Kevin Colyer",
               "y" : 176
            },
            {
               "drilldown" : "Cheok-Yin Fung",
               "name" : "#23: Cheok-Yin Fung",
               "y" : 174
            },
            {
               "drilldown" : "Mark Anderson",
               "y" : 174,
               "name" : "#24: Mark Anderson"
            },
            {
               "y" : 174,
               "name" : "#25: Markus Holzer",
               "drilldown" : "Markus Holzer"
            },
            {
               "drilldown" : "Kian-Meng Ang",
               "y" : 162,
               "name" : "#26: Kian-Meng Ang"
            },
            {
               "drilldown" : "Wanderdoc",
               "y" : 160,
               "name" : "#27: Wanderdoc"
            },
            {
               "y" : 156,
               "name" : "#28: Steven Wilson",
               "drilldown" : "Steven Wilson"
            },
            {
               "drilldown" : "Lubos Kolouch",
               "y" : 150,
               "name" : "#29: Lubos Kolouch"
            },
            {
               "drilldown" : "Shahed Nooshmand",
               "name" : "#30: Shahed Nooshmand",
               "y" : 140
            },
            {
               "drilldown" : "Duane Powell",
               "y" : 136,
               "name" : "#31: Duane Powell"
            },
            {
               "drilldown" : "Walt Mankowski",
               "name" : "#32: Walt Mankowski",
               "y" : 114
            },
            {
               "name" : "#33: Feng Chang",
               "y" : 112,
               "drilldown" : "Feng Chang"
            },
            {
               "y" : 110,
               "name" : "#34: Saif Ahmed",
               "drilldown" : "Saif Ahmed"
            },
            {
               "y" : 108,
               "name" : "#35: Burkhard Nickels",
               "drilldown" : "Burkhard Nickels"
            },
            {
               "y" : 106,
               "name" : "#36: Alicia Bielsa",
               "drilldown" : "Alicia Bielsa"
            },
            {
               "drilldown" : "Andrew Shitov",
               "name" : "#37: Andrew Shitov",
               "y" : 104
            },
            {
               "drilldown" : "Myoungjin Jeon",
               "y" : 104,
               "name" : "#38: Myoungjin Jeon"
            },
            {
               "name" : "#39: Francis Whittle",
               "y" : 96,
               "drilldown" : "Francis Whittle"
            },
            {
               "drilldown" : "Daniel Mantovani",
               "name" : "#40: Daniel Mantovani",
               "y" : 94
            },
            {
               "drilldown" : "Dave Cross",
               "y" : 88,
               "name" : "#41: Dave Cross"
            },
            {
               "y" : 86,
               "name" : "#42: Jorg Sommrey",
               "drilldown" : "Jorg Sommrey"
            },
            {
               "name" : "#43: Pete Houston",
               "y" : 86,
               "drilldown" : "Pete Houston"
            },
            {
               "drilldown" : "Niels van Dijke",
               "name" : "#44: Niels van Dijke",
               "y" : 84
            },
            {
               "drilldown" : "Mark Senn",
               "name" : "#45: Mark Senn",
               "y" : 80
            },
            {
               "drilldown" : "Simon Green",
               "name" : "#46: Simon Green",
               "y" : 76
            },
            {
               "name" : "#47: Gustavo Chaves",
               "y" : 72,
               "drilldown" : "Gustavo Chaves"
            },
            {
               "drilldown" : "James Smith",
               "y" : 72,
               "name" : "#48: James Smith"
            },
            {
               "drilldown" : "Yozen Hernandez",
               "y" : 70,
               "name" : "#49: Yozen Hernandez"
            },
            {
               "drilldown" : "Guillermo Ramos",
               "name" : "#50: Guillermo Ramos",
               "y" : 64
            }
         ],
         "name" : "Perl Weekly Challenge Leaders"
      }
   ],
   "yAxis" : {
      "title" : {
         "text" : "Total Score"
      }
   },
   "drilldown" : {
      "series" : [
         {
            "data" : [
               [
                  "Blog",
                  142
               ],
               [
                  "Perl",
                  149
               ],
               [
                  "Raku",
                  154
               ]
            ],
            "name" : "Laurent Rosenfeld",
            "id" : "Laurent Rosenfeld"
         },
         {
            "id" : "Jaldhar H. Vyas",
            "name" : "Jaldhar H. Vyas",
            "data" : [
               [
                  "Blog",
                  57
               ],
               [
                  "Perl",
                  140
               ],
               [
                  "Raku",
                  139
               ]
            ]
         },
         {
            "name" : "Roger Bell_West",
            "data" : [
               [
                  "Blog",
                  62
               ],
               [
                  "Perl",
                  130
               ],
               [
                  "Raku",
                  97
               ]
            ],
            "id" : "Roger Bell_West"
         },
         {
            "name" : "Arne Sommer",
            "data" : [
               [
                  "Bash",
                  1
               ],
               [
                  "Blog",
                  80
               ],
               [
                  "Perl",
                  30
               ],
               [
                  "Raku",
                  160
               ]
            ],
            "id" : "Arne Sommer"
         },
         {
            "name" : "Javier Luque",
            "data" : [
               [
                  "Blog",
                  46
               ],
               [
                  "Perl",
                  92
               ],
               [
                  "Raku",
                  92
               ]
            ],
            "id" : "Javier Luque"
         },
         {
            "data" : [
               [
                  "Perl",
                  113
               ],
               [
                  "Raku",
                  113
               ]
            ],
            "name" : "Ruben Westerberg",
            "id" : "Ruben Westerberg"
         },
         {
            "data" : [
               [
                  "Blog",
                  25
               ],
               [
                  "Perl",
                  114
               ],
               [
                  "Raku",
                  76
               ]
            ],
            "name" : "Colin Crain",
            "id" : "Colin Crain"
         },
         {
            "data" : [
               [
                  "Blog",
                  52
               ],
               [
                  "Perl",
                  154
               ]
            ],
            "name" : "E. Choroba",
            "id" : "E. Choroba"
         },
         {
            "id" : "Athanasius",
            "name" : "Athanasius",
            "data" : [
               [
                  "Blog",
                  3
               ],
               [
                  "Perl",
                  117
               ],
               [
                  "Raku",
                  84
               ]
            ]
         },
         {
            "data" : [
               [
                  "Blog",
                  59
               ],
               [
                  "Perl",
                  68
               ],
               [
                  "Raku",
                  65
               ]
            ],
            "name" : "Mohammad S Anwar",
            "id" : "Mohammad S Anwar"
         },
         {
            "name" : "Adam Russell",
            "data" : [
               [
                  "Blog",
                  64
               ],
               [
                  "Perl",
                  114
               ],
               [
                  "Raku",
                  9
               ]
            ],
            "id" : "Adam Russell"
         },
         {
            "name" : "Joelle Maslak",
            "data" : [
               [
                  "Blog",
                  5
               ],
               [
                  "Perl",
                  81
               ],
               [
                  "Raku",
                  81
               ]
            ],
            "id" : "Joelle Maslak"
         },
         {
            "id" : "Simon Proctor",
            "data" : [
               [
                  "Blog",
                  12
               ],
               [
                  "Perl",
                  5
               ],
               [
                  "Raku",
                  141
               ]
            ],
            "name" : "Simon Proctor"
         },
         {
            "name" : "Dave Jacoby",
            "data" : [
               [
                  "Blog",
                  40
               ],
               [
                  "Perl",
                  114
               ],
               [
                  "Raku",
                  1
               ]
            ],
            "id" : "Dave Jacoby"
         },
         {
            "name" : "Ryan Thompson",
            "data" : [
               [
                  "Blog",
                  31
               ],
               [
                  "Perl",
                  57
               ],
               [
                  "Raku",
                  51
               ]
            ],
            "id" : "Ryan Thompson"
         },
         {
            "data" : [
               [
                  "Blog",
                  1
               ],
               [
                  "Perl",
                  134
               ]
            ],
            "name" : "Duncan C. White",
            "id" : "Duncan C. White"
         },
         {
            "id" : "Luca Ferrari",
            "name" : "Luca Ferrari",
            "data" : [
               [
                  "Blog",
                  66
               ],
               [
                  "Raku",
                  68
               ]
            ]
         },
         {
            "data" : [
               [
                  "Perl",
                  55
               ],
               [
                  "Raku",
                  74
               ]
            ],
            "name" : "Ulrich Rieke",
            "id" : "Ulrich Rieke"
         },
         {
            "id" : "Andrezgz",
            "data" : [
               [
                  "Perl",
                  115
               ]
            ],
            "name" : "Andrezgz"
         },
         {
            "name" : "Yet Ebreo",
            "data" : [
               [
                  "Blog",
                  6
               ],
               [
                  "Perl",
                  81
               ],
               [
                  "Raku",
                  21
               ]
            ],
            "id" : "Yet Ebreo"
         },
         {
            "name" : "Noud Aldenhoven",
            "data" : [
               [
                  "Blog",
                  1
               ],
               [
                  "Raku",
                  93
               ]
            ],
            "id" : "Noud Aldenhoven"
         },
         {
            "id" : "Kevin Colyer",
            "data" : [
               [
                  "Blog",
                  2
               ],
               [
                  "Perl",
                  2
               ],
               [
                  "Raku",
                  84
               ]
            ],
            "name" : "Kevin Colyer"
         },
         {
            "data" : [
               [
                  "Blog",
                  20
               ],
               [
                  "Perl",
                  67
               ]
            ],
            "name" : "Cheok-Yin Fung",
            "id" : "Cheok-Yin Fung"
         },
         {
            "id" : "Mark Anderson",
            "data" : [
               [
                  "Perl",
                  19
               ],
               [
                  "Raku",
                  68
               ]
            ],
            "name" : "Mark Anderson"
         },
         {
            "id" : "Markus Holzer",
            "data" : [
               [
                  "Perl",
                  8
               ],
               [
                  "Raku",
                  79
               ]
            ],
            "name" : "Markus Holzer"
         },
         {
            "name" : "Kian-Meng Ang",
            "data" : [
               [
                  "Blog",
                  43
               ],
               [
                  "Perl",
                  38
               ]
            ],
            "id" : "Kian-Meng Ang"
         },
         {
            "data" : [
               [
                  "Perl",
                  80
               ]
            ],
            "name" : "Wanderdoc",
            "id" : "Wanderdoc"
         },
         {
            "name" : "Steven Wilson",
            "data" : [
               [
                  "Blog",
                  4
               ],
               [
                  "Perl",
                  73
               ],
               [
                  "Raku",
                  1
               ]
            ],
            "id" : "Steven Wilson"
         },
         {
            "name" : "Lubos Kolouch",
            "data" : [
               [
                  "Perl",
                  75
               ]
            ],
            "id" : "Lubos Kolouch"
         },
         {
            "name" : "Shahed Nooshmand",
            "data" : [
               [
                  "Blog",
                  23
               ],
               [
                  "Perl",
                  1
               ],
               [
                  "Raku",
                  46
               ]
            ],
            "id" : "Shahed Nooshmand"
         },
         {
            "name" : "Duane Powell",
            "data" : [
               [
                  "Perl",
                  68
               ]
            ],
            "id" : "Duane Powell"
         },
         {
            "data" : [
               [
                  "Blog",
                  10
               ],
               [
                  "Perl",
                  47
               ]
            ],
            "name" : "Walt Mankowski",
            "id" : "Walt Mankowski"
         },
         {
            "id" : "Feng Chang",
            "name" : "Feng Chang",
            "data" : [
               [
                  "Perl",
                  22
               ],
               [
                  "Raku",
                  34
               ]
            ]
         },
         {
            "id" : "Saif Ahmed",
            "name" : "Saif Ahmed",
            "data" : [
               [
                  "Blog",
                  1
               ],
               [
                  "Perl",
                  54
               ]
            ]
         },
         {
            "id" : "Burkhard Nickels",
            "data" : [
               [
                  "Blog",
                  15
               ],
               [
                  "Perl",
                  31
               ],
               [
                  "Raku",
                  8
               ]
            ],
            "name" : "Burkhard Nickels"
         },
         {
            "id" : "Alicia Bielsa",
            "name" : "Alicia Bielsa",
            "data" : [
               [
                  "Perl",
                  44
               ],
               [
                  "Raku",
                  9
               ]
            ]
         },
         {
            "data" : [
               [
                  "Blog",
                  23
               ],
               [
                  "Perl",
                  1
               ],
               [
                  "Raku",
                  28
               ]
            ],
            "name" : "Andrew Shitov",
            "id" : "Andrew Shitov"
         },
         {
            "data" : [
               [
                  "Blog",
                  4
               ],
               [
                  "Perl",
                  24
               ],
               [
                  "Raku",
                  24
               ]
            ],
            "name" : "Myoungjin Jeon",
            "id" : "Myoungjin Jeon"
         },
         {
            "id" : "Francis Whittle",
            "name" : "Francis Whittle",
            "data" : [
               [
                  "Blog",
                  9
               ],
               [
                  "Raku",
                  39
               ]
            ]
         },
         {
            "id" : "Daniel Mantovani",
            "data" : [
               [
                  "Blog",
                  2
               ],
               [
                  "Perl",
                  45
               ]
            ],
            "name" : "Daniel Mantovani"
         },
         {
            "data" : [
               [
                  "Blog",
                  2
               ],
               [
                  "Perl",
                  42
               ]
            ],
            "name" : "Dave Cross",
            "id" : "Dave Cross"
         },
         {
            "id" : "Jorg Sommrey",
            "data" : [
               [
                  "Perl",
                  43
               ]
            ],
            "name" : "Jorg Sommrey"
         },
         {
            "id" : "Pete Houston",
            "data" : [
               [
                  "Perl",
                  43
               ]
            ],
            "name" : "Pete Houston"
         },
         {
            "id" : "Niels van Dijke",
            "name" : "Niels van Dijke",
            "data" : [
               [
                  "Perl",
                  42
               ]
            ]
         },
         {
            "id" : "Mark Senn",
            "data" : [
               [
                  "Blog",
                  10
               ],
               [
                  "Raku",
                  30
               ]
            ],
            "name" : "Mark Senn"
         },
         {
            "data" : [
               [
                  "Blog",
                  12
               ],
               [
                  "Perl",
                  26
               ]
            ],
            "name" : "Simon Green",
            "id" : "Simon Green"
         },
         {
            "id" : "Gustavo Chaves",
            "name" : "Gustavo Chaves",
            "data" : [
               [
                  "Blog",
                  4
               ],
               [
                  "Perl",
                  32
               ]
            ]
         },
         {
            "name" : "James Smith",
            "data" : [
               [
                  "Perl",
                  26
               ],
               [
                  "Raku",
                  10
               ]
            ],
            "id" : "James Smith"
         },
         {
            "id" : "Yozen Hernandez",
            "data" : [
               [
                  "Blog",
                  14
               ],
               [
                  "Perl",
                  21
               ]
            ],
            "name" : "Yozen Hernandez"
         },
         {
            "data" : [
               [
                  "Perl",
                  32
               ]
            ],
            "name" : "Guillermo Ramos",
            "id" : "Guillermo Ramos"
         }
      ]
   },
   "chart" : {
      "type" : "column"
   }
}
