{
   "yAxis" : {
      "title" : {
         "text" : "Total Solutions"
      }
   },
   "series" : [
      {
         "name" : "Perl Weekly Challenge - 097",
         "colorByPoint" : 1,
         "data" : [
            {
               "drilldown" : "Aaron Smith",
               "y" : 3,
               "name" : "Aaron Smith"
            },
            {
               "name" : "Abigail",
               "y" : 4,
               "drilldown" : "Abigail"
            },
            {
               "drilldown" : "Adam Russell",
               "name" : "Adam Russell",
               "y" : 3
            },
            {
               "drilldown" : "Alexander Pankoff",
               "y" : 2,
               "name" : "Alexander Pankoff"
            },
            {
               "drilldown" : "Arne Sommer",
               "name" : "Arne Sommer",
               "y" : 5
            },
            {
               "drilldown" : "Athanasius",
               "y" : 4,
               "name" : "Athanasius"
            },
            {
               "name" : "Cheok-Yin Fung",
               "y" : 2,
               "drilldown" : "Cheok-Yin Fung"
            },
            {
               "y" : 5,
               "name" : "Colin Crain",
               "drilldown" : "Colin Crain"
            },
            {
               "drilldown" : "Cristina Heredia",
               "y" : 2,
               "name" : "Cristina Heredia"
            },
            {
               "drilldown" : "Dave Jacoby",
               "y" : 3,
               "name" : "Dave Jacoby"
            },
            {
               "drilldown" : "Duncan C. White",
               "name" : "Duncan C. White",
               "y" : 2
            },
            {
               "y" : 2,
               "name" : "E. Choroba",
               "drilldown" : "E. Choroba"
            },
            {
               "y" : 4,
               "name" : "Flavio Poletti",
               "drilldown" : "Flavio Poletti"
            },
            {
               "y" : 2,
               "name" : "Gustavo Chaves",
               "drilldown" : "Gustavo Chaves"
            },
            {
               "name" : "James Smith",
               "y" : 3,
               "drilldown" : "James Smith"
            },
            {
               "drilldown" : "Jan Hoogenraad",
               "name" : "Jan Hoogenraad",
               "y" : 2
            },
            {
               "drilldown" : "Jan Krnavek",
               "name" : "Jan Krnavek",
               "y" : 2
            },
            {
               "drilldown" : "Joan Mimosinnet",
               "y" : 2,
               "name" : "Joan Mimosinnet"
            },
            {
               "name" : "Jorg Sommrey",
               "y" : 2,
               "drilldown" : "Jorg Sommrey"
            },
            {
               "drilldown" : "Kai Burgdorf",
               "y" : 2,
               "name" : "Kai Burgdorf"
            },
            {
               "drilldown" : "Lance Wicks",
               "y" : 2,
               "name" : "Lance Wicks"
            },
            {
               "drilldown" : "Laurent Rosenfeld",
               "name" : "Laurent Rosenfeld",
               "y" : 5
            },
            {
               "drilldown" : "Lubos Kolouch",
               "y" : 2,
               "name" : "Lubos Kolouch"
            },
            {
               "y" : 4,
               "name" : "Luca Ferrari",
               "drilldown" : "Luca Ferrari"
            },
            {
               "y" : 2,
               "name" : "Mark Anderson",
               "drilldown" : "Mark Anderson"
            },
            {
               "y" : 2,
               "name" : "Niels van Dijke",
               "drilldown" : "Niels van Dijke"
            },
            {
               "drilldown" : "Nuno Vieira",
               "name" : "Nuno Vieira",
               "y" : 2
            },
            {
               "drilldown" : "Paulo Custodio",
               "y" : 2,
               "name" : "Paulo Custodio"
            },
            {
               "drilldown" : "Pete Houston",
               "name" : "Pete Houston",
               "y" : 2
            },
            {
               "drilldown" : "Philip Hood",
               "name" : "Philip Hood",
               "y" : 2
            },
            {
               "drilldown" : "Robbie Hatley",
               "y" : 2,
               "name" : "Robbie Hatley"
            },
            {
               "name" : "Roger Bell_West",
               "y" : 5,
               "drilldown" : "Roger Bell_West"
            },
            {
               "drilldown" : "Simon Green",
               "y" : 3,
               "name" : "Simon Green"
            },
            {
               "name" : "Simon Proctor",
               "y" : 1,
               "drilldown" : "Simon Proctor"
            },
            {
               "y" : 4,
               "name" : "Stuart Little",
               "drilldown" : "Stuart Little"
            },
            {
               "name" : "Ulrich Rieke",
               "y" : 4,
               "drilldown" : "Ulrich Rieke"
            },
            {
               "name" : "W. Luis Mochan",
               "y" : 3,
               "drilldown" : "W. Luis Mochan"
            },
            {
               "drilldown" : "Wanderdoc",
               "y" : 2,
               "name" : "Wanderdoc"
            }
         ]
      }
   ],
   "chart" : {
      "type" : "column"
   },
   "legend" : {
      "enabled" : 0
   },
   "tooltip" : {
      "followPointer" : 1,
      "headerFormat" : "<span style='font-size:11px'>{series.name}</span><br/>",
      "pointFormat" : "<span style='color:{point.color}'>{point.name}</span>: <b>{point.y:f}</b><br/>"
   },
   "subtitle" : {
      "text" : "[Champions: 38] Last updated at 2021-01-31 22:57:46 GMT"
   },
   "drilldown" : {
      "series" : [
         {
            "data" : [
               [
                  "Raku",
                  2
               ],
               [
                  "Blog",
                  1
               ]
            ],
            "id" : "Aaron Smith",
            "name" : "Aaron Smith"
         },
         {
            "id" : "Abigail",
            "data" : [
               [
                  "Perl",
                  2
               ],
               [
                  "Blog",
                  2
               ]
            ],
            "name" : "Abigail"
         },
         {
            "name" : "Adam Russell",
            "data" : [
               [
                  "Perl",
                  2
               ],
               [
                  "Blog",
                  1
               ]
            ],
            "id" : "Adam Russell"
         },
         {
            "name" : "Alexander Pankoff",
            "data" : [
               [
                  "Perl",
                  2
               ]
            ],
            "id" : "Alexander Pankoff"
         },
         {
            "name" : "Arne Sommer",
            "data" : [
               [
                  "Perl",
                  2
               ],
               [
                  "Raku",
                  2
               ],
               [
                  "Blog",
                  1
               ]
            ],
            "id" : "Arne Sommer"
         },
         {
            "name" : "Athanasius",
            "id" : "Athanasius",
            "data" : [
               [
                  "Perl",
                  2
               ],
               [
                  "Raku",
                  2
               ]
            ]
         },
         {
            "id" : "Cheok-Yin Fung",
            "data" : [
               [
                  "Perl",
                  2
               ]
            ],
            "name" : "Cheok-Yin Fung"
         },
         {
            "name" : "Colin Crain",
            "data" : [
               [
                  "Perl",
                  2
               ],
               [
                  "Raku",
                  2
               ],
               [
                  "Blog",
                  1
               ]
            ],
            "id" : "Colin Crain"
         },
         {
            "id" : "Cristina Heredia",
            "data" : [
               [
                  "Perl",
                  2
               ]
            ],
            "name" : "Cristina Heredia"
         },
         {
            "id" : "Dave Jacoby",
            "data" : [
               [
                  "Perl",
                  2
               ],
               [
                  "Blog",
                  1
               ]
            ],
            "name" : "Dave Jacoby"
         },
         {
            "data" : [
               [
                  "Perl",
                  2
               ]
            ],
            "id" : "Duncan C. White",
            "name" : "Duncan C. White"
         },
         {
            "data" : [
               [
                  "Perl",
                  2
               ]
            ],
            "id" : "E. Choroba",
            "name" : "E. Choroba"
         },
         {
            "name" : "Flavio Poletti",
            "data" : [
               [
                  "Perl",
                  2
               ],
               [
                  "Blog",
                  2
               ]
            ],
            "id" : "Flavio Poletti"
         },
         {
            "data" : [
               [
                  "Perl",
                  2
               ]
            ],
            "id" : "Gustavo Chaves",
            "name" : "Gustavo Chaves"
         },
         {
            "id" : "James Smith",
            "data" : [
               [
                  "Perl",
                  2
               ],
               [
                  "Blog",
                  1
               ]
            ],
            "name" : "James Smith"
         },
         {
            "data" : [
               [
                  "Perl",
                  2
               ]
            ],
            "id" : "Jan Hoogenraad",
            "name" : "Jan Hoogenraad"
         },
         {
            "name" : "Jan Krnavek",
            "id" : "Jan Krnavek",
            "data" : [
               [
                  "Raku",
                  2
               ]
            ]
         },
         {
            "name" : "Joan Mimosinnet",
            "id" : "Joan Mimosinnet",
            "data" : [
               [
                  "Raku",
                  2
               ]
            ]
         },
         {
            "name" : "Jorg Sommrey",
            "id" : "Jorg Sommrey",
            "data" : [
               [
                  "Perl",
                  2
               ]
            ]
         },
         {
            "name" : "Kai Burgdorf",
            "data" : [
               [
                  "Perl",
                  2
               ]
            ],
            "id" : "Kai Burgdorf"
         },
         {
            "data" : [
               [
                  "Perl",
                  1
               ],
               [
                  "Blog",
                  1
               ]
            ],
            "id" : "Lance Wicks",
            "name" : "Lance Wicks"
         },
         {
            "name" : "Laurent Rosenfeld",
            "data" : [
               [
                  "Perl",
                  2
               ],
               [
                  "Raku",
                  2
               ],
               [
                  "Blog",
                  1
               ]
            ],
            "id" : "Laurent Rosenfeld"
         },
         {
            "id" : "Lubos Kolouch",
            "data" : [
               [
                  "Perl",
                  2
               ]
            ],
            "name" : "Lubos Kolouch"
         },
         {
            "data" : [
               [
                  "Raku",
                  2
               ],
               [
                  "Blog",
                  2
               ]
            ],
            "id" : "Luca Ferrari",
            "name" : "Luca Ferrari"
         },
         {
            "name" : "Mark Anderson",
            "data" : [
               [
                  "Raku",
                  2
               ]
            ],
            "id" : "Mark Anderson"
         },
         {
            "name" : "Niels van Dijke",
            "data" : [
               [
                  "Perl",
                  2
               ]
            ],
            "id" : "Niels van Dijke"
         },
         {
            "id" : "Nuno Vieira",
            "data" : [
               [
                  "Perl",
                  2
               ]
            ],
            "name" : "Nuno Vieira"
         },
         {
            "id" : "Paulo Custodio",
            "data" : [
               [
                  "Perl",
                  2
               ]
            ],
            "name" : "Paulo Custodio"
         },
         {
            "name" : "Pete Houston",
            "id" : "Pete Houston",
            "data" : [
               [
                  "Perl",
                  2
               ]
            ]
         },
         {
            "name" : "Philip Hood",
            "id" : "Philip Hood",
            "data" : [
               [
                  "Raku",
                  2
               ]
            ]
         },
         {
            "id" : "Robbie Hatley",
            "data" : [
               [
                  "Perl",
                  2
               ]
            ],
            "name" : "Robbie Hatley"
         },
         {
            "id" : "Roger Bell_West",
            "data" : [
               [
                  "Perl",
                  2
               ],
               [
                  "Raku",
                  2
               ],
               [
                  "Blog",
                  1
               ]
            ],
            "name" : "Roger Bell_West"
         },
         {
            "name" : "Simon Green",
            "data" : [
               [
                  "Perl",
                  2
               ],
               [
                  "Blog",
                  1
               ]
            ],
            "id" : "Simon Green"
         },
         {
            "data" : [
               [
                  "Raku",
                  1
               ]
            ],
            "id" : "Simon Proctor",
            "name" : "Simon Proctor"
         },
         {
            "name" : "Stuart Little",
            "id" : "Stuart Little",
            "data" : [
               [
                  "Perl",
                  2
               ],
               [
                  "Raku",
                  2
               ]
            ]
         },
         {
            "id" : "Ulrich Rieke",
            "data" : [
               [
                  "Perl",
                  2
               ],
               [
                  "Raku",
                  2
               ]
            ],
            "name" : "Ulrich Rieke"
         },
         {
            "id" : "W. Luis Mochan",
            "data" : [
               [
                  "Perl",
                  2
               ],
               [
                  "Blog",
                  1
               ]
            ],
            "name" : "W. Luis Mochan"
         },
         {
            "name" : "Wanderdoc",
            "data" : [
               [
                  "Perl",
                  2
               ]
            ],
            "id" : "Wanderdoc"
         }
      ]
   },
   "plotOptions" : {
      "series" : {
         "borderWidth" : 0,
         "dataLabels" : {
            "format" : "{point.y}",
            "enabled" : 1
         }
      }
   },
   "xAxis" : {
      "type" : "category"
   },
   "title" : {
      "text" : "Perl Weekly Challenge - 097"
   }
}
