{
   "tooltip" : {
      "pointFormat" : "<span style='color:{point.color}'>{point.name}</span>: <b>{point.y:f}</b><br/>",
      "headerFormat" : "<span style='font-size:11px'>{series.name}</span><br/>",
      "followPointer" : 1
   },
   "drilldown" : {
      "series" : [
         {
            "id" : "Alicia Bielsa",
            "data" : [
               [
                  "Perl",
                  2
               ],
               [
                  "Raku",
                  1
               ]
            ],
            "name" : "Alicia Bielsa"
         },
         {
            "name" : "Andrezgz",
            "data" : [
               [
                  "Perl",
                  2
               ]
            ],
            "id" : "Andrezgz"
         },
         {
            "id" : "Arne Sommer",
            "data" : [
               [
                  "Raku",
                  2
               ],
               [
                  "Blog",
                  1
               ]
            ],
            "name" : "Arne Sommer"
         },
         {
            "name" : "Athanasius",
            "id" : "Athanasius",
            "data" : [
               [
                  "Perl",
                  1
               ],
               [
                  "Raku",
                  1
               ]
            ]
         },
         {
            "data" : [
               [
                  "Perl",
                  2
               ]
            ],
            "id" : "Dave Jacoby",
            "name" : "Dave Jacoby"
         },
         {
            "id" : "E. Choroba",
            "data" : [
               [
                  "Perl",
                  2
               ]
            ],
            "name" : "E. Choroba"
         },
         {
            "name" : "Javier Luque",
            "data" : [
               [
                  "Perl",
                  2
               ],
               [
                  "Raku",
                  2
               ],
               [
                  "Blog",
                  1
               ]
            ],
            "id" : "Javier Luque"
         },
         {
            "id" : "Jen Guerra",
            "data" : [
               [
                  "Perl",
                  1
               ]
            ],
            "name" : "Jen Guerra"
         },
         {
            "name" : "Lubos Kolouch",
            "data" : [
               [
                  "Perl",
                  2
               ]
            ],
            "id" : "Lubos Kolouch"
         },
         {
            "name" : "Luca Ferrari",
            "id" : "Luca Ferrari",
            "data" : [
               [
                  "Raku",
                  2
               ],
               [
                  "Blog",
                  2
               ]
            ]
         },
         {
            "name" : "Mark Anderson",
            "id" : "Mark Anderson",
            "data" : [
               [
                  "Raku",
                  2
               ]
            ]
         },
         {
            "name" : "Markus Holzer",
            "data" : [
               [
                  "Raku",
                  2
               ]
            ],
            "id" : "Markus Holzer"
         },
         {
            "name" : "Mohammad S Anwar",
            "id" : "Mohammad S Anwar",
            "data" : [
               [
                  "Perl",
                  2
               ],
               [
                  "Raku",
                  2
               ],
               [
                  "Blog",
                  1
               ]
            ]
         },
         {
            "data" : [
               [
                  "Raku",
                  2
               ]
            ],
            "id" : "Noud Aldenhoven",
            "name" : "Noud Aldenhoven"
         },
         {
            "data" : [
               [
                  "Perl",
                  2
               ],
               [
                  "Raku",
                  1
               ]
            ],
            "id" : "Roger Bell West",
            "name" : "Roger Bell West"
         },
         {
            "data" : [
               [
                  "Perl",
                  2
               ],
               [
                  "Raku",
                  2
               ]
            ],
            "id" : "Ruben Westerberg",
            "name" : "Ruben Westerberg"
         },
         {
            "name" : "Saif Ahmed",
            "id" : "Saif Ahmed",
            "data" : [
               [
                  "Perl",
                  2
               ]
            ]
         },
         {
            "name" : "Simon Proctor",
            "id" : "Simon Proctor",
            "data" : [
               [
                  "Raku",
                  2
               ]
            ]
         },
         {
            "id" : "Ulrich Rieke",
            "data" : [
               [
                  "Perl",
                  1
               ],
               [
                  "Raku",
                  2
               ]
            ],
            "name" : "Ulrich Rieke"
         },
         {
            "id" : "User Person",
            "data" : [
               [
                  "Perl",
                  2
               ]
            ],
            "name" : "User Person"
         },
         {
            "name" : "Wanderdoc",
            "data" : [
               [
                  "Perl",
                  2
               ]
            ],
            "id" : "Wanderdoc"
         },
         {
            "data" : [
               [
                  "Perl",
                  2
               ]
            ],
            "id" : "Yet Ebreo",
            "name" : "Yet Ebreo"
         }
      ]
   },
   "xAxis" : {
      "type" : "category"
   },
   "title" : {
      "text" : "Perl Weekly Challenge - 055"
   },
   "chart" : {
      "type" : "column"
   },
   "subtitle" : {
      "text" : "[Champions: 22] Last updated at 2020-04-12 17:57:23 GMT"
   },
   "series" : [
      {
         "colorByPoint" : 1,
         "data" : [
            {
               "drilldown" : "Alicia Bielsa",
               "y" : 3,
               "name" : "Alicia Bielsa"
            },
            {
               "y" : 2,
               "drilldown" : "Andrezgz",
               "name" : "Andrezgz"
            },
            {
               "y" : 3,
               "drilldown" : "Arne Sommer",
               "name" : "Arne Sommer"
            },
            {
               "name" : "Athanasius",
               "drilldown" : "Athanasius",
               "y" : 2
            },
            {
               "y" : 2,
               "drilldown" : "Dave Jacoby",
               "name" : "Dave Jacoby"
            },
            {
               "name" : "E. Choroba",
               "drilldown" : "E. Choroba",
               "y" : 2
            },
            {
               "y" : 5,
               "drilldown" : "Javier Luque",
               "name" : "Javier Luque"
            },
            {
               "name" : "Jen Guerra",
               "y" : 1,
               "drilldown" : "Jen Guerra"
            },
            {
               "name" : "Lubos Kolouch",
               "y" : 2,
               "drilldown" : "Lubos Kolouch"
            },
            {
               "drilldown" : "Luca Ferrari",
               "y" : 4,
               "name" : "Luca Ferrari"
            },
            {
               "drilldown" : "Mark Anderson",
               "y" : 2,
               "name" : "Mark Anderson"
            },
            {
               "name" : "Markus Holzer",
               "drilldown" : "Markus Holzer",
               "y" : 2
            },
            {
               "name" : "Mohammad S Anwar",
               "y" : 5,
               "drilldown" : "Mohammad S Anwar"
            },
            {
               "drilldown" : "Noud Aldenhoven",
               "y" : 2,
               "name" : "Noud Aldenhoven"
            },
            {
               "name" : "Roger Bell West",
               "y" : 3,
               "drilldown" : "Roger Bell West"
            },
            {
               "y" : 4,
               "drilldown" : "Ruben Westerberg",
               "name" : "Ruben Westerberg"
            },
            {
               "name" : "Saif Ahmed",
               "drilldown" : "Saif Ahmed",
               "y" : 2
            },
            {
               "name" : "Simon Proctor",
               "y" : 2,
               "drilldown" : "Simon Proctor"
            },
            {
               "drilldown" : "Ulrich Rieke",
               "y" : 3,
               "name" : "Ulrich Rieke"
            },
            {
               "drilldown" : "User Person",
               "y" : 2,
               "name" : "User Person"
            },
            {
               "name" : "Wanderdoc",
               "y" : 2,
               "drilldown" : "Wanderdoc"
            },
            {
               "name" : "Yet Ebreo",
               "drilldown" : "Yet Ebreo",
               "y" : 2
            }
         ],
         "name" : "Perl Weekly Challenge - 055"
      }
   ],
   "legend" : {
      "enabled" : 0
   },
   "yAxis" : {
      "title" : {
         "text" : "Total Solutions"
      }
   },
   "plotOptions" : {
      "series" : {
         "borderWidth" : 0,
         "dataLabels" : {
            "format" : "{point.y}",
            "enabled" : 1
         }
      }
   }
}
