{
   "legend" : {
      "enabled" : "false"
   },
   "yAxis" : {
      "title" : {
         "text" : null
      },
      "min" : 0
   },
   "subtitle" : {
      "text" : "Last updated at 2021-03-19 05:15:24 GMT"
   },
   "tooltip" : {
      "pointFormat" : "<b>{point.y:.0f}</b>"
   },
   "series" : [
      {
         "name" : "Contributions",
         "dataLabels" : {
            "style" : {
               "fontSize" : "13px",
               "fontFamily" : "Verdana, sans-serif"
            },
            "format" : "{point.y:.0f}",
            "align" : "right",
            "y" : 10,
            "color" : "#FFFFFF",
            "rotation" : -90,
            "enabled" : "true"
         },
         "data" : [
            [
               "Blog",
               1402
            ],
            [
               "Perl",
               4886
            ],
            [
               "Raku",
               3124
            ]
         ]
      }
   ],
   "xAxis" : {
      "type" : "category",
      "labels" : {
         "style" : {
            "fontFamily" : "Verdana, sans-serif",
            "fontSize" : "13px"
         }
      }
   },
   "title" : {
      "text" : "Perl Weekly Challenge Contributions [2019 - 2020]"
   },
   "chart" : {
      "type" : "column"
   }
}
