{
   "tooltip" : {
      "followPointer" : "true",
      "headerFormat" : "<span style=\"font-size:11px\"></span>",
      "pointFormat" : "<span style=\"color:{point.color}\">Challenge {point.name}</span>: <b>{point.y:f}</b><br/>"
   },
   "yAxis" : {
      "title" : {
         "text" : "Total Solutions"
      }
   },
   "plotOptions" : {
      "series" : {
         "borderWidth" : 0,
         "dataLabels" : {
            "enabled" : 1,
            "format" : "{point.y}"
         }
      }
   },
   "legend" : {
      "enabled" : "false"
   },
   "drilldown" : {
      "series" : [
         {
            "name" : "001",
            "id" : "001",
            "data" : [
               [
                  "Perl 5",
                  76
               ],
               [
                  "Perl 6",
                  37
               ],
               [
                  "Blog",
                  10
               ]
            ]
         },
         {
            "name" : "002",
            "id" : "002",
            "data" : [
               [
                  "Perl 5",
                  63
               ],
               [
                  "Perl 6",
                  32
               ],
               [
                  "Blog",
                  9
               ]
            ]
         },
         {
            "name" : "003",
            "id" : "003",
            "data" : [
               [
                  "Perl 5",
                  32
               ],
               [
                  "Perl 6",
                  26
               ],
               [
                  "Blog",
                  8
               ]
            ]
         },
         {
            "id" : "004",
            "name" : "004",
            "data" : [
               [
                  "Perl 5",
                  46
               ],
               [
                  "Perl 6",
                  29
               ],
               [
                  "Blog",
                  9
               ]
            ]
         },
         {
            "id" : "005",
            "name" : "005",
            "data" : [
               [
                  "Perl 5",
                  33
               ],
               [
                  "Perl 6",
                  22
               ],
               [
                  "Blog",
                  11
               ]
            ]
         },
         {
            "name" : "006",
            "id" : "006",
            "data" : [
               [
                  "Perl 5",
                  27
               ],
               [
                  "Perl 6",
                  14
               ],
               [
                  "Blog",
                  6
               ]
            ]
         },
         {
            "data" : [
               [
                  "Perl 5",
                  26
               ],
               [
                  "Perl 6",
                  20
               ],
               [
                  "Blog",
                  8
               ]
            ],
            "id" : "007",
            "name" : "007"
         },
         {
            "name" : "008",
            "id" : "008",
            "data" : [
               [
                  "Perl 5",
                  38
               ],
               [
                  "Perl 6",
                  20
               ],
               [
                  "Blog",
                  9
               ]
            ]
         },
         {
            "id" : "009",
            "name" : "009",
            "data" : [
               [
                  "Perl 5",
                  33
               ],
               [
                  "Perl 6",
                  18
               ],
               [
                  "Blog",
                  11
               ]
            ]
         },
         {
            "name" : "010",
            "id" : "010",
            "data" : [
               [
                  "Perl 5",
                  32
               ],
               [
                  "Perl 6",
                  17
               ],
               [
                  "Blog",
                  9
               ]
            ]
         },
         {
            "name" : "011",
            "id" : "011",
            "data" : [
               [
                  "Perl 5",
                  41
               ],
               [
                  "Perl 6",
                  26
               ],
               [
                  "Blog",
                  8
               ]
            ]
         },
         {
            "name" : "012",
            "id" : "012",
            "data" : [
               [
                  "Perl 5",
                  43
               ],
               [
                  "Perl 6",
                  28
               ],
               [
                  "Blog",
                  9
               ]
            ]
         },
         {
            "name" : "013",
            "id" : "013",
            "data" : [
               [
                  "Perl 5",
                  3
               ],
               [
                  "Perl 6",
                  4
               ],
               [
                  "Blog",
                  0
               ]
            ]
         }
      ]
   },
   "title" : {
      "text" : "Perl Weekly Challenge Language"
   },
   "series" : [
      {
         "data" : [
            {
               "drilldown" : "001",
               "name" : "#001",
               "y" : 123
            },
            {
               "name" : "#002",
               "y" : 104,
               "drilldown" : "002"
            },
            {
               "name" : "#003",
               "y" : 66,
               "drilldown" : "003"
            },
            {
               "drilldown" : "004",
               "name" : "#004",
               "y" : 84
            },
            {
               "name" : "#005",
               "y" : 66,
               "drilldown" : "005"
            },
            {
               "drilldown" : "006",
               "name" : "#006",
               "y" : 47
            },
            {
               "drilldown" : "007",
               "name" : "#007",
               "y" : 54
            },
            {
               "drilldown" : "008",
               "y" : 67,
               "name" : "#008"
            },
            {
               "drilldown" : "009",
               "name" : "#009",
               "y" : 62
            },
            {
               "y" : 58,
               "name" : "#010",
               "drilldown" : "010"
            },
            {
               "y" : 75,
               "name" : "#011",
               "drilldown" : "011"
            },
            {
               "y" : 80,
               "name" : "#012",
               "drilldown" : "012"
            },
            {
               "drilldown" : "013",
               "name" : "#013",
               "y" : 7
            }
         ],
         "name" : "Perl Weekly Challenge Languages",
         "colorByPoint" : "true"
      }
   ],
   "xAxis" : {
      "type" : "category"
   },
   "subtitle" : {
      "text" : "Click the columns to drilldown the language breakdown. Last updated at 2019-06-17 17:07:07 GMT"
   },
   "chart" : {
      "type" : "column"
   }
}
